{
    "name": "Social Media Dashboard Theme",
    "dataColors": [
        "#F94144",
        "#F3722C",
        "#F9C74F",
        "#90BE6D",
        "#43AA8B",
        "#577590"
    ],
    "background": "#FFFFFF",
    "foreground": "#333333",
    "tableAccent": "#F3722C",
    "visualStyles": {
        "*": {
            "*": {
                "color": [
                    {
                        "solid": {
                            "color": "#333333"
                        }
                    }
                ],
                "background": [
                    {
                        "solid": {
                            "color": "#FFFFFF"
                        }
                    }
                ]
            }
        }
    }
}